text_block_local/__init__.py
text_block_local/text_block.py
text_block_local-0.0.59.dist-info/METADATA
text_block_local-0.0.59.dist-info/WHEEL
text_block_local-0.0.59.dist-info/top_level.txt
text_block_local-0.0.59.dist-info/RECORD
