Metadata-Version: 2.4
Name: text-block-local
Version: 0.0.59
Home-page: https://github.com/circles-zone/text-block-local-python-package
Author: Circles
Author-email: info@circlez.ai
Classifier: Programming Language :: Python :: 3
Classifier: License :: Other/Proprietary License
Classifier: Operating System :: OS Independent
Requires-Dist: logger-local>=0.0.135
Requires-Dist: database-mysql-local>=0.0.291
Requires-Dist: user-context-remote>=0.0.75
Requires-Dist: profile-local>=0.0.65
Requires-Dist: person-local>=0.0.76
Requires-Dist: fields-local>=0.0.9
Dynamic: author
Dynamic: author-email
Dynamic: classifier
Dynamic: description
Dynamic: description-content-type
Dynamic: home-page
Dynamic: requires-dist
